drf_dynamic_read/__init__.py
drf_dynamic_read/exceptions.py
drf_dynamic_read/serializers.py
drf_dynamic_read/utils.py
drf_dynamic_read/views.py
drf_dynamic_read-0.1.1.dist-info/LICENSE
drf_dynamic_read-0.1.1.dist-info/METADATA
drf_dynamic_read-0.1.1.dist-info/WHEEL
drf_dynamic_read-0.1.1.dist-info/top_level.txt
drf_dynamic_read-0.1.1.dist-info/zip-safe
drf_dynamic_read-0.1.1.dist-info/RECORD
