Metadata-Version: 2.1
Name: drf-dynamic-read
Version: 0.1.1
Summary: A utility to improve and optimise read operations(querying and serialization of data) for Django Rest Framework based applications
Home-page: https://github.com/GirishKotra/drf-dynamic-read
Author: Girish Kotra
Author-email: girish934@gmail.com
License: MIT
Keywords: drf restframework rest_framework django_rest_framework serializers
Platform: UNKNOWN
Classifier: Development Status :: 3 - Alpha
Classifier: License :: OSI Approved :: MIT License
Classifier: Programming Language :: Python :: 3
Classifier: Framework :: Django
Classifier: Environment :: Web Environment
Requires-Python: >=3.6
License-File: LICENSE
Requires-Dist: Django (>=1.11.16)
Requires-Dist: djangorestframework (>=3.6.4)
